[
    {
      "id": "6422fd12803478946e55ca26",
      "balance": "$3,059.60",
      "picture": "https://ibb.co/NS7yHkR",
      "age": 30,
      "name": "Babar Azam"
    },
    {
      "id": "6422fd12398dd7194dac8e76",
      "balance": "$1,393.58",
      "picture": "https://ibb.co/4s5Bvpd",
      "age": 30,
      "name": "Rohit Sharma "
    },
    {
      "id": "6422fd1216c15ee81b7cf33f",
      "balance": "$3,784.53",
      "picture": "https://ibb.co/6Rj9Shf",
      "age": 21,
      "name": "Virat Kohli"
    },
    {
      "id": "6422fd122afd9dd18a750384",
      "balance": "$2,609.20",
      "picture": "https://ibb.co/dk9yK8r",
      "age": 35,
      "name": "Breet Lee"
    },
    {
      "id": "6422fd1291d1e837f73a0b38",
      "balance": "$2,943.05",
      "picture": "https://ibb.co/MVDRdD9",
      "age": 21,
      "name": "Bhumrah"
    },
    {
      "id": "6422fd1218c13b1c7590ea0f",
      "balance": "$2,881.21",
      "picture": "https://ibb.co/4gbDRKR",
      "age": 34,
      "name": "Pat Cummins"
    },
    {
      "id": "6422fd125f9d03ccf20cf52b",
      "balance": "$2,724.24",
      "picture": "https://ibb.co/xfd6t3R",
      "age": 37,
      "name": "Liton Das"
    },
    {
      "id": "6422fd128236afa87c515812",
      "balance": "$1,931.41",
      "picture": "https://ibb.co/QrNQc3z",
      "age": 32,
      "name": "Mashrafee"
    },
    {
      "id": "6422fd125da674fa6951bf4e",
      "balance": "$2,327.58",
      "picture": "https://ibb.co/Q6H0W3M",
      "age": 25,
      "name": "Ms Dhoni"
    }
  ]